{"data":[
            {"seq":1, "key":"hw_cost_per_core", "type": "text", "regex": "percentage", "isRequired": true, "validators":[], "ui_control":{"name": "hw_cost_per_core", "label": "HW Cost per core", "placeholder": "", "isDefault": false, "readOnly":false, "errorMsg": "Invalid format. Hint: 90.01", "style":""}},
            {"seq":2, "key":"hw_cost_maint_percentage", "type": "text", "regex": "percentage", "isRequired":true , "validators":[], "ui_control":{"name": "hw_cost_maint_percentage", "label": "Annual maintenance cost of HW core as % of HW value", "placeholder": "", "isDefault": false, "readOnly":false, "errorMsg": "Invalid format. Hint: 90.01", "style":""}},
            {"seq":3, "key":"storage_cost_per_gb", "type": "text", "regex": "percentage", "isRequired":true , "validators":[], "ui_control":{"name": "storage_cost_per_gb", "label": "Local Storage cost per GB", "placeholder": "", "isDefault": false, "readOnly":false, "errorMsg": "Invalid format. Hint: 90.01", "style":""}},
            {"seq":4, "key":"storage_cost_maint_percentage", "type": "text", "regex": "percentage", "isRequired":true , "validators":[], "ui_control":{"name": "storage_cost_maint_percentage", "label": "Annual maintenance cost of storage as % of HW value", "placeholder": "", "isDefault": false, "readOnly":false, "errorMsg": "Invalid format. Hint: 90.01", "style":""}},
            {"seq":5, "key":"network_cost_percentage", "type": "text", "regex": "percentage", "isRequired":true , "validators":[], "ui_control":{"name": "network_cost_percentage", "label": "Network HW/SW cost as % of HW/SW", "placeholder": "", "isDefault": false, "readOnly":false, "errorMsg": "Invalid format. Hint: 90.01", "style":""}},
            {"seq":6, "key":"network_cost_maint_percentage", "type": "text", "regex": "percentage", "isRequired":true , "validators":[], "ui_control":{"name": "network_cost_maint_percentage", "label": "Annual maintenance cost of network as % of HW value", "placeholder": "", "isDefault": false, "readOnly":false, "errorMsg": "Invalid format. Hint: 90.01", "style":""}},
            {"seq":7, "key":"os_license_cost", "type": "text", "regex": "percentage", "isRequired":true , "validators":[], "ui_control":{"name": "os_license_cost", "label": "OS license (Redhat Linux, Oracle Enterprise Linux, etc.) (annual per processor/socket)", "placeholder": "", "isDefault": false, "readOnly":false, "errorMsg": "Invalid format. Hint: 90.01", "style":""}},
            {"seq":8, "key":"avg_core_per_socket", "type": "text", "regex": "percentage", "isRequired":true , "validators":[], "ui_control":{"name": "avg_core_per_socket", "label": "Average cores per socket", "placeholder": "", "isDefault": false, "readOnly":false, "errorMsg": "Invalid format. Hint: 90.01", "style":""}}
        ]
}
    